__init__.py
pleonasty/LLM_Result.py
pleonasty/Pleonast.py
pleonasty/__init__.py
pleonasty/_buildPrompt.py
pleonasty/analyze_text.py
pleonasty/batch_analyze_csv_to_csv.py
pleonasty/batch_analyze_to_csv.py
pleonasty/chat_mode.py
pleonasty/convert_prompt_to_template_str.py
pleonasty/generate_csv_outputs.py
pleonasty/set_message_contexts.py
pleonasty-0.3.7.dist-info/licenses/LICENSE
pleonasty-0.3.7.dist-info/METADATA
pleonasty-0.3.7.dist-info/WHEEL
pleonasty-0.3.7.dist-info/top_level.txt
pleonasty-0.3.7.dist-info/RECORD
