Metadata-Version: 2.4
Name: pleonasty
Version: 0.3.7
Summary: A very simple abstraction for LLMs to get single responses to a given input.
Author-email: "Ryan L. Boyd" <ryan@ryanboyd.io>
Project-URL: Homepage, https://github.com/ryanboyd/pleonasty
Project-URL: Issues, https://github.com/ryanboyd/pleonasty/issues
Classifier: Programming Language :: Python :: 3
Classifier: License :: OSI Approved :: MIT License
Classifier: Operating System :: OS Independent
Requires-Python: >=3.10
License-File: LICENSE
Requires-Dist: vllm>=0.9.1
Requires-Dist: bitsandbytes>=0.46.0
Dynamic: license-file
